odoo/addons/ssi_l10n_id_taxform_faktur_pajak_operating_unit/README.rst
odoo/addons/ssi_l10n_id_taxform_faktur_pajak_operating_unit/__init__.py
odoo/addons/ssi_l10n_id_taxform_faktur_pajak_operating_unit/__manifest__.py
odoo/addons/ssi_l10n_id_taxform_faktur_pajak_operating_unit/i18n/ssi_l10n_id_taxform_faktur_pajak_operating_unit.pot
odoo/addons/ssi_l10n_id_taxform_faktur_pajak_operating_unit/models/__init__.py
odoo/addons/ssi_l10n_id_taxform_faktur_pajak_operating_unit/models/faktur_pajak_keluaran.py
odoo/addons/ssi_l10n_id_taxform_faktur_pajak_operating_unit/security/ir_rule/faktur_pajak_keluaran.xml
odoo/addons/ssi_l10n_id_taxform_faktur_pajak_operating_unit/security/res_group/faktur_pajak_keluaran.xml
odoo/addons/ssi_l10n_id_taxform_faktur_pajak_operating_unit/static/description/icon.png
odoo/addons/ssi_l10n_id_taxform_faktur_pajak_operating_unit/views/faktur_pajak_keluaran_views.xml
odoo14_addon_ssi_l10n_id_taxform_faktur_pajak_operating_unit-14.0.1.2.0.dist-info/METADATA
odoo14_addon_ssi_l10n_id_taxform_faktur_pajak_operating_unit-14.0.1.2.0.dist-info/WHEEL
odoo14_addon_ssi_l10n_id_taxform_faktur_pajak_operating_unit-14.0.1.2.0.dist-info/top_level.txt
odoo14_addon_ssi_l10n_id_taxform_faktur_pajak_operating_unit-14.0.1.2.0.dist-info/RECORD
